{"cameraMode":{"drawMode":0,"name":"Shaded","section":"Shading Mode"},"sceneLighting":true,"audioPlay":false,"sceneViewState":{"m_AlwaysRefresh":false,"showFog":true,"showSkybox":true,"showFlares":true,"showImageEffects":true,"showParticleSystems":true,"showVisualEffectGraphs":true,"m_FxEnabled":true},"in2DMode":false,"pivot":{"x":36.68531799316406,"y":34.55704116821289,"z":-11.387285232543946},"rotation":{"x":-0.007496741600334644,"y":0.029393084347248079,"z":0.00022047117818146944,"w":0.9995402097702026},"size":28.537790298461915,"orthographic":false}